simplest_notebook/__init__.py
simplest_notebook/index.html
simplest_notebook/build/0.bundle.js
simplest_notebook/build/0.bundle.js.map
simplest_notebook/build/058e48cbbee6cdbfb2a2e6dab347f245.woff
simplest_notebook/build/1.bundle.js
simplest_notebook/build/1.bundle.js.map
simplest_notebook/build/3326c360137c2d6a6909d0c4303e502a.eot
simplest_notebook/build/674f50d287a8c48dc19ba404d20fe713.eot
simplest_notebook/build/895bc7de59413bb8029ac83cac8c9e1b.woff
simplest_notebook/build/aa8f3ca044cd237f87b69d0cb364887a.ttf
simplest_notebook/build/af7ae505a9eed503f8b8e6982036873e.woff2
simplest_notebook/build/b06871f281fee6b241d60582ae9369b9.ttf
simplest_notebook/build/b6382c6d9ffca4a1c50f58a17fce15a9.ttf
simplest_notebook/build/bundle.js
simplest_notebook/build/bundle.js.map
simplest_notebook/build/commands.d.ts
simplest_notebook/build/commands.js
simplest_notebook/build/e666d692a7dc07ea69886dfcec837c3c.eot
simplest_notebook/build/fee66e712a8a08eef5805a46892932ad.woff
simplest_notebook/build/index.d.ts
simplest_notebook/build/index.js
simplest_notebook/build/tsconfig.tsbuildinfo
simplest_notebook-0.0.9.data/data/etc/jupyter/jupyter_notebook_config.d/simplest-notebook-serverextension.json
simplest_notebook-0.0.9.dist-info/.ipynb_checkpoints/not-zip-safe-checkpoint
simplest_notebook-0.0.9.dist-info/METADATA
simplest_notebook-0.0.9.dist-info/WHEEL
simplest_notebook-0.0.9.dist-info/entry_points.txt
simplest_notebook-0.0.9.dist-info/top_level.txt
simplest_notebook-0.0.9.dist-info/RECORD
