Metadata-Version: 2.1
Name: simplest-notebook
Version: 0.0.9
Summary: UNKNOWN
Home-page: https://github.com/yuvipanda/simplest-notebook
Author: Yuvi Panda
Author-email: yuvipanda@gmail.com
License: BSD 3-Clause
Platform: UNKNOWN
Classifier: Framework :: Jupyter
Requires-Python: >=3.5
Requires-Dist: notebook
